djdg_oauth
