Metadata-Version: 1.1
Name: djdg-django-oauth
Version: 0.0.21
Summary: djdg OAuth2 method for Django
Home-page: UNKNOWN
Author: zaneYang
Author-email: zane.yang@hey900.com
License: BSD
Keywords: djdg django oauth2 oauthlib
Platform: UNKNOWN
Classifier: Development Status :: 1 - Planning
Classifier: Environment :: Web Environment
Classifier: Framework :: Django :: 1.9
Classifier: License :: OSI Approved :: BSD License
Classifier: Operating System :: POSIX :: Linux
Classifier: Programming Language :: Python :: 2.7
Classifier: Topic :: Software Development :: Libraries :: Python Modules
